{"api_extra_is-schema.md":"3b08e7de","api_extra_use-property.md":"69db5920","api_extra_use-schema.md":"36e0373e","api_extra_version.md":"94e3d4f9","api_types_schema.md":"0dad586a","api_index.md":"bd6c5130","api_types_object-error.md":"2e8452e1","api_parse.md":"53f4f415","api_types_property-error.md":"66296aea","api_types_property-key.md":"7f8d8b60","api_schema.md":"1acf851f","changelog.md":"0a6cabda","index.md":"6ba1d610","guide_advanced_arrays-parsing.md":"a3ee5c4b","guide_advanced_benchmarks.md":"fcbe9f18","guide_advanced_types-upcasting.md":"83c34221","guide_advanced_typescript.md":"58b85a40","api_types_raw-schema-property.md":"4725685c","guide_installation.md":"2f29fcd9","guide_what-is-object-parser.md":"17aca5b4","guide_getting-started_quick-start.md":"a470e336","api_types_property-schema-return.md":"4d5cfb65","api_utilities_get-constructors.md":"0eb64e32","api_types_async-function-constructor.md":"a395759c","api_types_schema-return.md":"8ad47c8a","api_parse-async.md":"87ed4d68","api_property.md":"78437169","api_types_array-constructor.md":"4405130b","api_types_general-error.md":"e210d100","api_single.md":"f7b459f8","guide_getting-started_methods.md":"507032ae","guide_getting-started_schemas.md":"c8f08b22","api_types_constructor-return.md":"451991f6","api_types_generator-function-constructor.md":"7a498ce5","api_types_property-schema-raw.md":"c0b67f84","api_types_raw-schema.md":"3631a023","api_types_constructor.md":"296145c5","api_types_schema-return-keys.md":"7bc63f51","api_extra_is-property.md":"6e1bc358","api_utilities_errors.md":"047d7897","api_types_property-schema.md":"c891e1e1","api_utilities_is-primitive-constructors.md":"38ad5889","api_utilities_is-constructors.md":"3f8a0226","api_utilities_generator-function.md":"8592fd6a","api_utilities_async-function.md":"acd50e16"}
